neutools/__init__.py
neutools/__main__.py
neutools/debug.py
neutools/globalvars.py
neutools/plugin.py
neutools/templates.py
neutools-0.2.3.dist-info/METADATA
neutools-0.2.3.dist-info/WHEEL
neutools-0.2.3.dist-info/entry_points.txt
neutools-0.2.3.dist-info/top_level.txt
neutools-0.2.3.dist-info/RECORD
