Metadata-Version: 2.2
Name: neutools
Version: 0.2.3
Summary: neutron panel debug tools
Author-email: cxykevin <cxykevin@yeah.net>
Project-URL: homepage, https://gitee.com/cxy_kevin/neutron
Project-URL: repository, https://gitee.com/cxy_kevin/neutron
Classifier: Programming Language :: Python :: 3.13
Classifier: Programming Language :: Python :: 3.12
Classifier: Programming Language :: Python :: 3.11
Classifier: License :: OSI Approved :: GNU General Public License v2 (GPLv2)
Classifier: Operating System :: POSIX :: Linux
Requires-Python: >=3.11
Requires-Dist: typer
